crispo/__init__.py
crispo/advanced_crispo.py
crispo/crispo.py
crispo/crispo_core.py
crispo/nas_pipeline.py
crispo/predictor_evaluator.py
crispo/solution_registry.py
crispo/transfer_learning_pipeline.py
crispo-1.0.3.dist-info/licenses/LICENSE
crispo-1.0.3.dist-info/METADATA
crispo-1.0.3.dist-info/WHEEL
crispo-1.0.3.dist-info/entry_points.txt
crispo-1.0.3.dist-info/top_level.txt
crispo-1.0.3.dist-info/RECORD
